gurobi_logtools/__init__.py
gurobi_logtools/__main__.py
gurobi_logtools/api.py
gurobi_logtools/cli.py
gurobi_logtools/colors.py
gurobi_logtools/constants.py
gurobi_logtools/gurobi_colors.py
gurobi_logtools/helpers.py
gurobi_logtools/plotting.py
gurobi_logtools/parameters/__init__.py
gurobi_logtools/parameters/defaults.py
gurobi_logtools/parameters/pretty.py
gurobi_logtools/parameters/data/1000.json
gurobi_logtools/parameters/data/1001.json
gurobi_logtools/parameters/data/1002.json
gurobi_logtools/parameters/data/1003.json
gurobi_logtools/parameters/data/1100.json
gurobi_logtools/parameters/data/1101.json
gurobi_logtools/parameters/data/1102.json
gurobi_logtools/parameters/data/1103.json
gurobi_logtools/parameters/data/1200.json
gurobi_logtools/parameters/data/1201.json
gurobi_logtools/parameters/data/1202.json
gurobi_logtools/parameters/data/1203.json
gurobi_logtools/parameters/data/800.json
gurobi_logtools/parameters/data/801.json
gurobi_logtools/parameters/data/810.json
gurobi_logtools/parameters/data/811.json
gurobi_logtools/parameters/data/900.json
gurobi_logtools/parameters/data/901.json
gurobi_logtools/parameters/data/902.json
gurobi_logtools/parameters/data/903.json
gurobi_logtools/parameters/data/910.json
gurobi_logtools/parameters/data/911.json
gurobi_logtools/parameters/data/912.json
gurobi_logtools/parameters/data/950.json
gurobi_logtools/parameters/data/951.json
gurobi_logtools/parameters/data/952.json
gurobi_logtools/parameters/data/__init__.py
gurobi_logtools/parameters/data/descriptions.json
gurobi_logtools/parsers/__init__.py
gurobi_logtools/parsers/barrier.py
gurobi_logtools/parsers/continuous.py
gurobi_logtools/parsers/header.py
gurobi_logtools/parsers/nodelog.py
gurobi_logtools/parsers/norel.py
gurobi_logtools/parsers/presolve.py
gurobi_logtools/parsers/pretree_solutions.py
gurobi_logtools/parsers/simplex.py
gurobi_logtools/parsers/single_log.py
gurobi_logtools/parsers/termination.py
gurobi_logtools/parsers/util.py
gurobi_logtools-4.0.1.dist-info/METADATA
gurobi_logtools-4.0.1.dist-info/WHEEL
gurobi_logtools-4.0.1.dist-info/licenses/LICENSE
gurobi_logtools-4.0.1.dist-info/RECORD
