Metadata-Version: 2.4
Name: gurobi-logtools
Version: 4.0.1
Summary: Gurobi log file tools for parsing and exploring data
Project-URL: Homepage, https://github.com/Gurobi/gurobi-logtools
Author-email: "Gurobi Optimization, LLC" <support@gurobi.com>
License:                         Apache License
License-File: LICENSE
Classifier: License :: OSI Approved :: Apache Software License
Classifier: Operating System :: OS Independent
Classifier: Programming Language :: Python :: 3
Classifier: Programming Language :: Python :: 3 :: Only
Classifier: Programming Language :: Python :: 3.9
Classifier: Programming Language :: Python :: 3.10
Classifier: Programming Language :: Python :: 3.11
Classifier: Programming Language :: Python :: 3.12
Classifier: Programming Language :: Python :: 3.13
Requires-Python: >=3.9
Requires-Dist: ipywidgets
Requires-Dist: nbformat>=4.2.0
Requires-Dist: numpy
Requires-Dist: pandas
Requires-Dist: plotly
Requires-Dist: xlsxwriter
